pynucseg/__init__.py
pynucseg/base.py
PyNucSeg-0.0.9.dist-info/LICENSE
PyNucSeg-0.0.9.dist-info/METADATA
PyNucSeg-0.0.9.dist-info/WHEEL
PyNucSeg-0.0.9.dist-info/top_level.txt
PyNucSeg-0.0.9.dist-info/RECORD
