Metadata-Version: 2.1
Name: PyNucSeg
Version: 0.0.9
Summary: Segment fluorescent nucleus, and measure the area, and the mean intensity per nucleus.
Home-page: https://github.com/pganes/PyNucSeg
Author: Ganesh Pandey
Author-email: gpande3@uic.edu
Classifier: Programming Language :: Python :: 3.10
License-File: LICENSE
Requires-Dist: numpy
Requires-Dist: stardist
Requires-Dist: napari
Requires-Dist: scikit-image
Requires-Dist: tensorflow
Requires-Dist: pyqt5
Provides-Extra: dev
Requires-Dist: pytest (>=3.7) ; extra == 'dev'
Requires-Dist: twine ; extra == 'dev'
